augly_jp/__init__.py
augly_jp/text/__init__.py
augly_jp/text/augmenters/__init__.py
augly_jp/text/augmenters/sentence.py
augly_jp/text/augmenters/utils.py
augly_jp/text/augmenters/word.py
augly_jp/text/functional/__init__.py
augly_jp/text/functional/sentence.py
augly_jp/text/functional/word.py
augly_jp/text/transforms/__init__.py
augly_jp/text/transforms/sentence.py
augly_jp/text/transforms/word.py
augly_jp-2021.9.30.dist-info/LICENSE
augly_jp-2021.9.30.dist-info/WHEEL
augly_jp-2021.9.30.dist-info/METADATA
augly_jp-2021.9.30.dist-info/RECORD
