Metadata-Version: 2.1
Name: augly-jp
Version: 2021.9.30
Summary: Data Augmentation for Japanese Text
Home-page: https://github.com/chck/AugLy-jp
License: MIT
Author: chck
Author-email: shimekiri.today@gmail.com
Requires-Python: >=3.7.1,<4.0.0
Classifier: License :: OSI Approved :: MIT License
Classifier: Programming Language :: Python :: 3
Classifier: Programming Language :: Python :: 3.8
Classifier: Programming Language :: Python :: 3.9
Requires-Dist: augly (>=0.1.7,<0.2.0)
Requires-Dist: chikkarpy (>=0.1.0,<0.2.0)
Requires-Dist: dartsclone (>=0.9.0,<0.10.0)
Requires-Dist: fugashi[unidic-lite] (>=1.1.1,<2.0.0)
Requires-Dist: gensim (>=4.0.1,<5.0.0)
Requires-Dist: ginza (>=5.0.1,<6.0.0)
Requires-Dist: ja-ginza-electra (>=5.0.0,<6.0.0)
Requires-Dist: numpy (>=1.19.2,<1.20.0)
Requires-Dist: python-Levenshtein (>=0.12.2,<0.13.0)
Requires-Dist: python-magic-bin (>=0.4.14,<0.5.0); sys_platform == "win32" or sys_platform == "darwin"
Requires-Dist: sentencepiece (>=0.1.96,<0.2.0)
Requires-Dist: tenacity (>=8.0.1,<9.0.0)
Requires-Dist: torch (>=1.9.0,<2.0.0)
Requires-Dist: tqdm (>=4.62.2,<5.0.0)
Requires-Dist: transformers (<4.10.0)
Project-URL: Repository, https://github.com/chck/AugLy-jp
